clock.v
`timescale 1ps/1ps

module clock(c);

    output reg c;
    initial 
        begin
            c = 1'b0;
            repeat(30)
                #10 c = ~c;
        end
endmodule

clock_tb.v
`include "clock.v"
`timescale 1ps/1ps

module clock_tb;
    wire c;
    clock uut(.c(c));
    
    initial
    begin
        $dumpfile("clock.vcd");
        $dumpvars(0, clock_tb);
    end

    initial
    begin
        $monitor("t=%2d, c =%1b", $time, c);
        #350 $finish;
    end
endmodule

clock.vcd
$date
	Thu Jan 25 22:33:29 2024
$end
$version
	Icarus Verilog
$end
$timescale
	1ps
$end
$scope module clock_tb $end
$var wire 1 ! c $end
$scope module uut $end
$var reg 1 ! c $end
$upscope $end
$upscope $end
$enddefinitions $end
$comment Show the parameter values. $end
$dumpall
$end
#0
$dumpvars
0!
$end
#10
1!
#20
0!
#30
1!
#40
0!
#50
1!
#60
0!
#70
1!
#80
0!
#90
1!
#100
0!
#110
1!
#120
0!
#130
1!
#140
0!
#150
1!
#160
0!
#170
1!
#180
0!
#190
1!
#200
0!
#210
1!
#220
0!
#230
1!
#240
0!
#250
1!
#260
0!
#270
1!
#280
0!
#290
1!
#300
0!
