Comparator.v
`timescale 1ns/1ns

module Comparator1bit (A,B,Y);
    
    input A,B;
    output [5:0] Y;

    assign Y[5] = ~((A)^(B));
    assign Y[4] = ((A)^(B));
    assign Y[3] = ((A)&(~(B)));
    assign Y[2] = ((~(A))&(B));
    assign Y[1] = ((A)|(~(B)));
    assign Y[0] = ((~(A))|(B));
    
endmodule

Comparator2bit.v
`include "Comparator.v"
`timescale 1ns/1ns

module Comparator2bit (A,B,Y);

    input [1:0] A,B;
    output [5:0] Y;

    wire [5:0] w0, w1;

    Comparator1bit Cm0(A[0], B[0], w0);
    Comparator1bit Cm1(A[1], B[1], w1);

    assign Y[5] = (w0[5] & w1[5]);
    assign Y[4] = (w0[4] | w1[4]);
    assign Y[3] = ((w1[3] & (w0[2]|w0[3]|w0[5]))|(w1[5] & w0[3]));
    assign Y[2] = ((w1[2] & (w0[2]|w0[3]|w0[5]))|(w1[5] & w0[2]));
    assign Y[1] = (Y[5]|Y[3]);
    assign Y[0] = (Y[5]|Y[2]);
    
endmodule

Comparator2bit_tb.v
`include "Comparator2bit.v"
`timescale 1ns/1ns

module Comparator2bit_tb;

    reg [1:0] A,B;
    wire [5:0] Y;

    Comparator2bit uut (.A(A), .B(B), .Y(Y));

    initial 
    begin
        $dumpfile("Comparator.vcd");
        $dumpvars(0, Comparator2bit_tb);

        #2 A = 2'b00; B = 2'b00;
        #2 A = 2'b00; B = 2'b01;    
        #2 A = 2'b00; B = 2'b10;
        #2 A = 2'b00; B = 2'b11;
        #2 A = 2'b01; B = 2'b00;
        #2 A = 2'b01; B = 2'b01;
        #2 A = 2'b01; B = 2'b10;
        #2 A = 2'b01; B = 2'b11;
        #2 A = 2'b10; B = 2'b00;
        #2 A = 2'b10; B = 2'b01;
        #2 A = 2'b10; B = 2'b10;
        #2 A = 2'b10; B = 2'b11;
        #2 A = 2'b11; B = 2'b00;
        #2 A = 2'b11; B = 2'b01;
        #2 A = 2'b11; B = 2'b10;
        #2 A = 2'b11; B = 2'b11;

    end
    initial
    begin
        $monitor("t=%2d, A=%2b, B=%2b, Y=%5b", $time,A,B,Y);
        #40 $finish;
    end
endmodule

Comparator.vcd
$date
	Tue Sep 26 15:12:57 2023
$end
$version
	Icarus Verilog
$end
$timescale
	1ns
$end
$scope module Comparator2bit_tb $end
$var wire 6 ! Y [5:0] $end
$var reg 2 " A [1:0] $end
$var reg 2 # B [1:0] $end
$scope module uut $end
$var wire 2 $ A [1:0] $end
$var wire 2 % B [1:0] $end
$var wire 6 & w1 [5:0] $end
$var wire 6 ' w0 [5:0] $end
$var wire 6 ( Y [5:0] $end
$scope module Cm0 $end
$var wire 1 ) A $end
$var wire 1 * B $end
$var wire 6 + Y [5:0] $end
$upscope $end
$scope module Cm1 $end
$var wire 1 , A $end
$var wire 1 - B $end
$var wire 6 . Y [5:0] $end
$upscope $end
$upscope $end
$upscope $end
$enddefinitions $end
$comment Show the parameter values. $end
$dumpall
$end
#0
$dumpvars
bx .
x-
x,
bx +
x*
x)
bx (
bx '
bx &
bx %
bx $
bx #
bx "
bx !
$end
#2
b100011 !
b100011 (
b100011 '
b100011 +
b100011 &
b100011 .
0*
0-
0)
0,
b0 #
b0 %
b0 "
b0 $
#4
b10101 !
b10101 (
b10101 '
b10101 +
1*
b1 #
b1 %
#6
b100011 '
b100011 +
b10101 &
b10101 .
0*
1-
b10 #
b10 %
#8
b10101 '
b10101 +
1*
b11 #
b11 %
#10
b11010 !
b11010 (
b100011 &
b100011 .
b11010 '
b11010 +
0*
0-
1)
b0 #
b0 %
b1 "
b1 $
#12
b100011 !
b100011 (
b100011 '
b100011 +
1*
b1 #
b1 %
#14
b10101 !
b10101 (
b11010 '
b11010 +
b10101 &
b10101 .
0*
1-
b10 #
b10 %
#16
b100011 '
b100011 +
1*
b11 #
b11 %
#18
b11010 !
b11010 (
b100011 '
b100011 +
b11010 &
b11010 .
0*
0-
0)
1,
b0 #
b0 %
b10 "
b10 $
#20
b10101 '
b10101 +
1*
b1 #
b1 %
#22
b100011 !
b100011 (
b100011 '
b100011 +
b100011 &
b100011 .
0*
1-
b10 #
b10 %
#24
b10101 !
b10101 (
b10101 '
b10101 +
1*
b11 #
b11 %
#26
b11010 !
b11010 (
b11010 &
b11010 .
b11010 '
b11010 +
0*
0-
1)
b0 #
b0 %
b11 "
b11 $
#28
b100011 '
b100011 +
1*
b1 #
b1 %
#30
b11010 '
b11010 +
b100011 &
b100011 .
0*
1-
b10 #
b10 %
#32
b100011 !
b100011 (
b100011 '
b100011 +
1*
b11 #
b11 %
