counter.v
module simplecounter (clk, rst, count);
    input clk, rst;
    output [3:0]count;
    reg [3:0]count;

    always @(posedge clk or posedge rst)
    begin
        if (rst)
            count = 4'b0;
        else
            count = count + 4'b1;
    end

endmodule

counter_tb.v
`timescale 1ns/1ns
`include "counter.v"

module counter_tb;

reg clk, rst;
wire [3:0]counter;
simplecounter uut(clk, rst, counter);
initial begin 
    $dumpfile("counter.vcd");
    $dumpvars(0, counter_tb);
    clk = 0;
    forever #5 clk = ~clk;
end
initial begin
    
    rst = 1;
    #20
    rst = 0;
    #100;
    
    $display("end of testing");
    $stop;
end
endmodule

counter.vcd
$date
	Thu Jun 08 17:32:16 2023
$end
$version
	Icarus Verilog
$end
$timescale
	1ns
$end
$scope module counter_tb $end
$var wire 4 ! counter [3:0] $end
$var reg 1 " clk $end
$var reg 1 # rst $end
$scope module uut $end
$var wire 1 " clk $end
$var wire 1 # rst $end
$var reg 4 $ count [3:0] $end
$upscope $end
$upscope $end
$enddefinitions $end
$comment Show the parameter values. $end
$dumpall
$end
#0
$dumpvars
b0 $
1#
0"
b0 !
$end
#5
1"
#10
0"
#15
1"
#20
0"
0#
#25
b1 !
b1 $
1"
#30
0"
#35
b10 !
b10 $
1"
#40
0"
#45
b11 !
b11 $
1"
#50
0"
#55
b100 !
b100 $
1"
#60
0"
#65
b101 !
b101 $
1"
#70
0"
#75
b110 !
b110 $
1"
#80
0"
#85
b111 !
b111 $
1"
#90
0"
#95
b1000 !
b1000 $
1"
#100
0"
#105
b1001 !
b1001 $
1"
#110
0"
#115
b1010 !
b1010 $
1"
